{
  "tiles" : [ {
    "scaleFactors" : [ 32, 16, 8, 4, 2, 1 ],
    "width" : 1024,
    "height" : 1024
  } ],
  "protocol" : "http://iiif.io/api/image",
  "sizes" : [ {
    "width" : 295,
    "height" : 211
  }, {
    "width" : 589,
    "height" : 421
  }, {
    "width" : 1177,
    "height" : 841
  }, {
    "width" : 2353,
    "height" : 1681
  }, {
    "width" : 4706,
    "height" : 3361
  }, {
    "width" : 9412,
    "height" : 6721
  } ],
  "profile" : "http://iiif.io/api/image/2/level0.json",
  "width" : 9412,
  "@id" : "https://kam535.github.io/hist2391/images/G4104C6A31892aC82",
  "@context" : "http://iiif.io/api/image/2/context.json",
  "height" : 6721
}